open3d_pycg/__init__.py
open3d_pycg/_build_config.py
open3d_pycg/libc++.so.1
open3d_pycg/libc++abi.so.1
open3d_pycg/libtbb.so.12
open3d_pycg/cpu/pybind.cpython-310-x86_64-linux-gnu.so
open3d_pycg/resources/Roboto-Bold.ttf
open3d_pycg/resources/Roboto-BoldItalic.ttf
open3d_pycg/resources/Roboto-License.txt
open3d_pycg/resources/Roboto-Medium.ttf
open3d_pycg/resources/Roboto-MediumItalic.ttf
open3d_pycg/resources/RobotoMono-Medium.ttf
open3d_pycg/resources/brightday_ibl.ktx
open3d_pycg/resources/brightday_skybox.ktx
open3d_pycg/resources/colorMap.filamat
open3d_pycg/resources/crossroads_ibl.ktx
open3d_pycg/resources/crossroads_skybox.ktx
open3d_pycg/resources/defaultGradient.png
open3d_pycg/resources/defaultLit.filamat
open3d_pycg/resources/defaultLitSSR.filamat
open3d_pycg/resources/defaultLitTransparency.filamat
open3d_pycg/resources/defaultTexture.png
open3d_pycg/resources/defaultUnlit.filamat
open3d_pycg/resources/defaultUnlitTransparency.filamat
open3d_pycg/resources/default_ibl.ktx
open3d_pycg/resources/default_skybox.ktx
open3d_pycg/resources/depth.filamat
open3d_pycg/resources/depth_value.filamat
open3d_pycg/resources/hall_ibl.ktx
open3d_pycg/resources/hall_skybox.ktx
open3d_pycg/resources/img_blit.filamat
open3d_pycg/resources/infiniteGroundPlane.filamat
open3d_pycg/resources/konzerthaus_ibl.ktx
open3d_pycg/resources/konzerthaus_skybox.ktx
open3d_pycg/resources/nightlights_ibl.ktx
open3d_pycg/resources/nightlights_skybox.ktx
open3d_pycg/resources/normals.filamat
open3d_pycg/resources/park2_ibl.ktx
open3d_pycg/resources/park2_skybox.ktx
open3d_pycg/resources/park_ibl.ktx
open3d_pycg/resources/park_skybox.ktx
open3d_pycg/resources/pillars_ibl.ktx
open3d_pycg/resources/pillars_skybox.ktx
open3d_pycg/resources/pointcloud.filamat
open3d_pycg/resources/streetlamp_ibl.ktx
open3d_pycg/resources/streetlamp_skybox.ktx
open3d_pycg/resources/ui_blit.filamat
open3d_pycg/resources/unlitBackground.filamat
open3d_pycg/resources/unlitGradient.filamat
open3d_pycg_cpu-0.19.0.dist-info/LICENSE.txt
open3d_pycg_cpu-0.19.0.dist-info/METADATA
open3d_pycg_cpu-0.19.0.dist-info/WHEEL
open3d_pycg_cpu-0.19.0.dist-info/top_level.txt
open3d_pycg_cpu-0.19.0.dist-info/RECORD
