Metadata-Version: 2.2
Name: open3d_pycg-cpu
Version: 0.19.0
Summary: Open3D: A Modern Library for 3D Data Processing.
Home-page: https://www.open3d.org
Author: Open3D Team
Author-email: open3d@intel.com
License: MIT
Project-URL: Documentation, https://www.open3d.org/docs
Project-URL: Source code, https://github.com/isl-org/Open3D
Project-URL: Issues, https://github.com/isl-org/Open3D/issues
Keywords: 3D reconstruction point cloud mesh RGB-D visualization
Classifier: Development Status :: 3 - Alpha
Classifier: Environment :: MacOS X
Classifier: Environment :: Win32 (MS Windows)
Classifier: Environment :: X11 Applications
Classifier: Intended Audience :: Developers
Classifier: Intended Audience :: Education
Classifier: Intended Audience :: Other Audience
Classifier: Intended Audience :: Science/Research
Classifier: License :: OSI Approved :: MIT License
Classifier: Natural Language :: English
Classifier: Operating System :: POSIX :: Linux
Classifier: Operating System :: MacOS :: MacOS X
Classifier: Operating System :: Microsoft :: Windows
Classifier: Programming Language :: C
Classifier: Programming Language :: C++
Classifier: Programming Language :: Python :: 3
Classifier: Programming Language :: Python :: 3.8
Classifier: Programming Language :: Python :: 3.9
Classifier: Programming Language :: Python :: 3.10
Classifier: Programming Language :: Python :: 3.11
Classifier: Programming Language :: Python :: 3.12
Classifier: Topic :: Education
Classifier: Topic :: Multimedia :: Graphics :: 3D Modeling
Classifier: Topic :: Multimedia :: Graphics :: 3D Rendering
Classifier: Topic :: Multimedia :: Graphics :: Capture
Classifier: Topic :: Multimedia :: Graphics :: Graphics Conversion
Classifier: Topic :: Multimedia :: Graphics :: Viewers
Classifier: Topic :: Scientific/Engineering
Classifier: Topic :: Scientific/Engineering :: Mathematics
Classifier: Topic :: Scientific/Engineering :: Visualization
Classifier: Topic :: Software Development :: Libraries :: Python Modules
Classifier: Topic :: Utilities
Provides: open3d
Provides: open3d_cpu
Provides: open3d_xpu
Obsoletes: open3d_python
Requires-Python: >=3.8
License-File: LICENSE.txt
Dynamic: author
Dynamic: author-email
Dynamic: classifier
Dynamic: description
Dynamic: description-content-type
Dynamic: home-page
Dynamic: keywords
Dynamic: license
Dynamic: obsoletes
Dynamic: project-url
Dynamic: provides
Dynamic: requires-dist
Dynamic: requires-python
Dynamic: summary
Requires-Dist: numpy (>=1.18.0)
